odoo/addons/test_base_geoengine/README.rst
odoo/addons/test_base_geoengine/__init__.py
odoo/addons/test_base_geoengine/__manifest__.py
odoo/addons/test_base_geoengine/models.py
odoo/addons/test_base_geoengine/views.xml
odoo/addons/test_base_geoengine/tests/__init__.py
odoo/addons/test_base_geoengine/tests/data.py
odoo/addons/test_base_geoengine/tests/test_base_geoengine.py
odoo11_addon_test_base_geoengine-11.0.1.0.0.dist-info/METADATA
odoo11_addon_test_base_geoengine-11.0.1.0.0.dist-info/RECORD
odoo11_addon_test_base_geoengine-11.0.1.0.0.dist-info/WHEEL
odoo11_addon_test_base_geoengine-11.0.1.0.0.dist-info/top_level.txt
